flash_amr_tools/__init__.py
flash_amr_tools/amr_tools.py
flash_amr_tools/block_tools.py
flash_amr_tools/zorder.py
flash_amr_tools-1.1.6.dist-info/licenses/LICENSE
flash_amr_tools-1.1.6.dist-info/METADATA
flash_amr_tools-1.1.6.dist-info/WHEEL
flash_amr_tools-1.1.6.dist-info/top_level.txt
flash_amr_tools-1.1.6.dist-info/RECORD
