Metadata-Version: 2.4
Name: flash_amr_tools
Version: 1.1.6
Summary: Small tool to create uniform data cubes of FLASH datasets. Port from bitbucket.org/pierrenbg/flash-amr-tools
Author-email: Keito Watanabe <k.wat8973@gmail.com>, Pierre Nürnberger <nuernb@ph1.uni-koeln.de>
License: BSD 3-Clause License
Project-URL: Homepage, https://github.com/kwat0308/flash-amr-tools
Project-URL: Issues, https://github.com/kwat0308/flash-amr-tools/issues
License-File: LICENSE
Requires-Dist: numpy
Requires-Dist: h5py
Provides-Extra: test
Requires-Dist: pytest; extra == "test"
Requires-Dist: pytest-cov; extra == "test"
Requires-Dist: urllib; extra == "test"
Dynamic: license-file
